pip_name_generator/__init__.py
pip_name_generator_example-0.1.0.dist-info/licenses/LICENSE
pip_name_generator_example-0.1.0.dist-info/METADATA
pip_name_generator_example-0.1.0.dist-info/WHEEL
pip_name_generator_example-0.1.0.dist-info/top_level.txt
pip_name_generator_example-0.1.0.dist-info/RECORD
