Metadata-Version: 2.4
Name: pip_name_generator_example
Version: 0.1.0
Summary: pip_name_generator: minimal package with a single public function to generate setup.py content.
Home-page: https://github.com/chigwell/pip_name_generator
Author: Eugene Evstafev
Author-email: hi@eugene.plus
License: MIT
Classifier: License :: OSI Approved :: MIT License
Classifier: Development Status :: 3 - Alpha
Classifier: Intended Audience :: Developers
Classifier: Programming Language :: Python :: 3
Classifier: Operating System :: OS Independent
Requires-Python: >=3.6
License-File: LICENSE
Dynamic: author
Dynamic: author-email
Dynamic: classifier
Dynamic: description
Dynamic: description-content-type
Dynamic: home-page
Dynamic: license
Dynamic: license-file
Dynamic: requires-python
Dynamic: summary
